serialpy/__init__.py
serialpy/__main__.py
serialpy/config.toml
serialpy/replace.py
serialpy/search.py
serialpy/utils.py
SerialPy-0.1.0.dist-info/LICENSE.txt
SerialPy-0.1.0.dist-info/METADATA
SerialPy-0.1.0.dist-info/WHEEL
SerialPy-0.1.0.dist-info/entry_points.txt
SerialPy-0.1.0.dist-info/top_level.txt
SerialPy-0.1.0.dist-info/RECORD
