Metadata-Version: 2.1
Name: SerialPy
Version: 0.1.0
Summary: A tool for working with serialized data
Author-email: Michael Montanaro <mcmontanaro01@gmail.com>
License:                     GNU GENERAL PUBLIC LICENSE
Project-URL: Homepage, https://github.com/montymi/serialpy
Keywords: serialization,yaml,json,toml,dictionary,search,replace,serial,data,OpenAPI,API,api,Config,Configuration
Classifier: License :: OSI Approved :: GNU General Public License (GPL)
Classifier: Programming Language :: Python
Classifier: Programming Language :: Python :: 3
Requires-Python: >=3.9
License-File: LICENSE.txt
Requires-Dist: PyYAML>=5.0
Provides-Extra: dev
Requires-Dist: pytest; extra == "dev"
